payrex/__init__.py
payrex/api_resource.py
payrex/client.py
payrex/config.py
payrex/error.py
payrex/http_client.py
payrex/entities/__init__.py
payrex/entities/billing_statement_entity.py
payrex/entities/billing_statement_line_item_entity.py
payrex/entities/checkout_session_entity.py
payrex/entities/customer_entity.py
payrex/entities/customer_session_entity.py
payrex/entities/deleted_entity.py
payrex/entities/event_entity.py
payrex/entities/listing_entity.py
payrex/entities/payment_entity.py
payrex/entities/payment_intent_entity.py
payrex/entities/payout_entity.py
payrex/entities/payout_transaction_entity.py
payrex/entities/refund_entity.py
payrex/entities/webhook_entity.py
payrex/exceptions/__init__.py
payrex/exceptions/authentication_invalid_exception.py
payrex/exceptions/base_exception.py
payrex/exceptions/request_invalid_exception.py
payrex/exceptions/resource_not_found_exception.py
payrex/exceptions/signature_invalid_exception.py
payrex/exceptions/value_unexpected_exception.py
payrex/services/__init__.py
payrex/services/base_service.py
payrex/services/billing_statement_line_item_service.py
payrex/services/billing_statement_service.py
payrex/services/checkout_session_service.py
payrex/services/customer_service.py
payrex/services/customer_session_service.py
payrex/services/payment_intent_service.py
payrex/services/payment_service.py
payrex/services/payout_service.py
payrex/services/refund_service.py
payrex/services/service_factory.py
payrex/services/webhook_service.py
payrex_python-1.7.3.dist-info/LICENSE
payrex_python-1.7.3.dist-info/METADATA
payrex_python-1.7.3.dist-info/WHEEL
payrex_python-1.7.3.dist-info/top_level.txt
payrex_python-1.7.3.dist-info/RECORD
