Metadata-Version: 2.1
Name: payrex-python
Version: 1.7.3
Summary: PayRex Python Library
Home-page: https://github.com/payrexhq/payrex-python
Author: PayRex
Author-email: support@payrexhq.com
License: MIT
Keywords: payrex
Classifier: Development Status :: 4 - Beta
Classifier: Intended Audience :: Developers
Classifier: Operating System :: OS Independent
Classifier: Programming Language :: Python
Classifier: Programming Language :: Python :: 3
Classifier: License :: OSI Approved :: MIT License
License-File: LICENSE
Requires-Dist: requests
